{
  "parent": "minecraft:recipes/root",
  "criteria": {
    "has_item": {
      "trigger": "minecraft:inventory_changed",
      "conditions": {
        "items": [
          {
            "items": [
              "minecraft:bone_block"
            ]
          }
        ]
      }
    },
    "has_the_recipe": {
      "trigger": "minecraft:recipe_unlocked",
      "conditions": {
        "recipe": "netherexp:stacked_bones"
      }
    }
  },
  "requirements": [
    [
      "has_the_recipe",
      "has_item"
    ]
  ],
  "rewards": {
    "recipes": [
      "netherexp:stacked_bones"
    ]
  }
}